pymodaq_plugins_greateyes/VERSION
pymodaq_plugins_greateyes/__init__.py
pymodaq_plugins_greateyes/daq_move_plugins/__init__.py
pymodaq_plugins_greateyes/daq_viewer_plugins/__init__.py
pymodaq_plugins_greateyes/daq_viewer_plugins/plugins_0D/__init__.py
pymodaq_plugins_greateyes/daq_viewer_plugins/plugins_1D/__init__.py
pymodaq_plugins_greateyes/daq_viewer_plugins/plugins_2D/__init__.py
pymodaq_plugins_greateyes/daq_viewer_plugins/plugins_2D/daq_2Dviewer_GreateyesCCD.py
pymodaq_plugins_greateyes/daq_viewer_plugins/plugins_ND/__init__.py
pymodaq_plugins_greateyes/extension/__init__.py
pymodaq_plugins_greateyes/hardware/__init__.py
pymodaq_plugins_greateyes/models/__init__.py
pymodaq_plugins_greateyes-1.0.2.dist-info/LICENSE
pymodaq_plugins_greateyes-1.0.2.dist-info/METADATA
pymodaq_plugins_greateyes-1.0.2.dist-info/WHEEL
pymodaq_plugins_greateyes-1.0.2.dist-info/entry_points.txt
pymodaq_plugins_greateyes-1.0.2.dist-info/top_level.txt
pymodaq_plugins_greateyes-1.0.2.dist-info/RECORD
