Metadata-Version: 2.1
Name: pymodaq-plugins-greateyes
Version: 1.0.2
Summary: some word about your plugin
Home-page: https://github.com/Attolab/pymodaq_plugins_greateyes
Author: PyMoDAQ plugin for instruments from Greateyes (ALEX, ELSE, GE XXXX)
Author-email: romain.geneaux@cea.fr
License: MIT
Classifier: Programming Language :: Python :: 3
Classifier: Development Status :: 5 - Production/Stable
Classifier: Environment :: Other Environment
Classifier: Intended Audience :: Science/Research
Classifier: Topic :: Scientific/Engineering :: Human Machine Interfaces
Classifier: Topic :: Scientific/Engineering :: Visualization
Classifier: License :: CeCILL-B Free Software License Agreement (CECILL-B)
Classifier: Operating System :: OS Independent
Classifier: Topic :: Software Development :: Libraries :: Python Modules
Classifier: Topic :: Software Development :: User Interfaces
License-File: LICENSE
Requires-Dist: toml
Requires-Dist: pymodaq >=4.0
